hocon/__init__.py
hocon/decoder.py
hocon/encoder.py
hocon-0.3.0.dist-info/LICENSE
hocon-0.3.0.dist-info/METADATA
hocon-0.3.0.dist-info/WHEEL
hocon-0.3.0.dist-info/top_level.txt
hocon-0.3.0.dist-info/RECORD
